py_rattler_build-0.48.0.dist-info/METADATA
py_rattler_build-0.48.0.dist-info/WHEEL
py_rattler_build-0.48.0.dist-info/license_files/LICENSE
rattler_build/recipe.py
rattler_build/__init__.py
rattler_build/recipe_generation.py
rattler_build/rattler_build.abi3.so
py_rattler_build-0.48.0.dist-info/RECORD
