Metadata-Version: 2.1
Name: py-rattler-build
Version: 0.48.0
Classifier: Development Status :: 3 - Alpha
Classifier: Intended Audience :: Developers
Classifier: License :: OSI Approved :: BSD License
Classifier: Programming Language :: Rust
Classifier: Programming Language :: Python :: Implementation :: CPython
Classifier: Programming Language :: Python :: Implementation :: PyPy
Classifier: Typing :: Typed
License-File: LICENSE
Summary: The fastest way to build conda packages programatically
Author-email: Wolf Vollprecht <w.vollprecht@gmail.com>
License: BSD-3-Clause
Requires-Python: >=3.8
Project-URL: Homepage, https://github.com/prefix-dev/rattler-build
Project-URL: Repository, https://github.com/prefix-dev/rattler-build
Project-URL: Issues, https://github.com/prefix-dev/rattler-build/labels/python-bindings
